{
    "success": true,
    "status": "passed",
    "selection": {
        "requestedJurisdiction": "chandler",
        "mode": "single"
    },
    "summary": {
        "tests": 1,
        "passed": 1,
        "failed": 0,
        "warnings": 0
    },
    "tests": [
        {
            "jurisdiction": "Chandler",
            "configPath": "data/authoritative/jurisdictions/chandler/zoning.json",
            "passed": true,
            "errors": [],
            "warnings": [],
            "metadata": {
                "verifiedDate": "2026-07-18",
                "verifiedBy": "Skyesoft",
                "testAddress": "3111 W Chandler Blvd, Chandler, AZ 85226",
                "testCoordinate": {
                    "latitude": 33.301499212767,
                    "longitude": -111.898592129302,
                    "expectedZoningCode": "PAD"
                }
            },
            "checks": {
                "resolverStatus": {
                    "expected": "resolved",
                    "actual": "resolved",
                    "passed": true
                },
                "zoningCode": {
                    "expected": "PAD",
                    "actual": "PAD",
                    "evaluated": true,
                    "passed": true
                }
            },
            "result": {
                "success": true,
                "status": "resolved",
                "reason": null,
                "message": "Base zoning resolved from the official jurisdiction source.",
                "jurisdictionName": "Chandler",
                "apnRaw": null,
                "zoningCode": "PAD",
                "zoningDescription": null,
                "zoningSource": "City of Chandler Development Services",
                "zoningVerifiedAt": 1784385429,
                "provider": "City of Chandler Development Services",
                "queryMethod": "point_intersection",
                "sourceUrl": "https://gis.chandleraz.gov/appsanonymous/rest/services/WAM/Planning/MapServer/6",
                "confidence": 95,
                "requiresReview": false,
                "candidateCount": 1,
                "candidates": [
                    {
                        "zoningCode": "PAD",
                        "zoningDescription": null,
                        "rawAttributes": {
                            "ZONE_CODE": "PAD"
                        }
                    }
                ],
                "raw": {
                    "attributes": {
                        "ZONE_CODE": "PAD"
                    }
                },
                "httpCode": null,
                "responseTimeMs": null,
                "elapsedMs": 297,
                "responseTime": 295
            }
        }
    ]
}